ai_web_helper/__init__.py
ai_web_helper/core.py
ai_web_helper-0.1.0.dist-info/METADATA
ai_web_helper-0.1.0.dist-info/WHEEL
ai_web_helper-0.1.0.dist-info/top_level.txt
ai_web_helper-0.1.0.dist-info/RECORD
